{"__type__":"cc.JsonAsset","_name":"LV_56","json":{"header":{"lv":0,"type":1,"star1":2,"star2":3,"star3":4,"totol":5,"balls":6,"items":7,"isAdvanceSmall":8},"data":["56",1,0,1400,2200,0,50,[{"offX":0,"offY":1,"type":2,"info":3},[3,6,1,{"num":50}],[4,6,1,{"num":50}],[5,6,1,{"num":50}],[6,6,1,{"num":50}],[7,6,1,{"num":50}],[2,7,1,{"num":45}],[3,7,1,{"num":45}],[4,7,1,{"num":45}],[5,7,1,{"num":45}],[6,7,1,{"num":45}],[7,7,1,{"num":45}],[8,7,1,{"num":45}],[1,8,1,{"num":50}],[3,8,1,{"num":50}],[4,8,1,{"num":50}],[6,8,1,{"num":50}],[7,8,1,{"num":50}],[9,8,1,{"num":50}],[1,9,1,{"num":50}],[4,9,1,{"num":50}],[5,9,1,{"num":50}],[6,9,1,{"num":50}],[9,9,1,{"num":50}],[2,10,1,{"num":47}],[5,10,1,{"num":50}],[8,10,1,{"num":47}],[3,11,1,{"num":47}],[4,11,1,{"num":47}],[6,11,1,{"num":47}],[7,11,1,{"num":47}],[2,12,1,{"num":60}],[3,12,1,{"num":30}],[4,12,1,{"num":30}],[5,12,1,{"num":60}],[6,12,1,{"num":30}],[7,12,1,{"num":30}],[8,12,1,{"num":60}],[5,11,9,{"num":30}],[3,9,8,{"num":1}],[7,9,8,{"num":1}],[0,8,6,{}],[10,8,6,{}],[2,13,1,{"num":52}],[3,13,1,{"num":30}],[4,13,1,{"num":30}],[6,13,1,{"num":30}],[7,13,1,{"num":30}],[8,13,1,{"num":52}],[3,14,1,{"num":30}],[4,14,1,{"num":30}],[6,14,1,{"num":30}],[7,14,1,{"num":30}],[5,13,9,{"isOpen":false,"num":26}],[9,13,8,{"num":1}],[2,14,1,{"num":52}],[5,14,1,{"num":52}],[8,14,1,{"num":52}],[1,14,8,{"num":1}],[0,14,6,{}],[3,15,1,{"num":45}],[7,15,1,{"num":45}],[5,8,11,{"num":50}],[0,7,38,{}],[10,7,38,{}]],false]}}
